examples/anvil_test.py
x402_notify/__init__.py
x402_notify/agent_server.py
x402_notify/async_client.py
x402_notify/async_native.py
x402_notify/client.py
x402_notify/queue.py
x402_notify-0.1.0.dist-info/METADATA
x402_notify-0.1.0.dist-info/WHEEL
x402_notify-0.1.0.dist-info/top_level.txt
x402_notify-0.1.0.dist-info/RECORD
