Metadata-Version: 2.4
Name: x402-notify
Version: 0.1.0
Summary: Send permissionless Telegram notifications via x402 protocol
Author: x402 Team
License: MIT
Project-URL: Homepage, https://github.com/x402-notify
Requires-Python: >=3.8
Requires-Dist: requests>=2.28.0
Requires-Dist: web3>=6.0.0
Requires-Dist: eth-account>=0.8.0
Provides-Extra: http
Requires-Dist: httpx>=0.24.0; extra == "http"
